huojiweiguoba/__init__.py
huojiweiguoba/decorator.py
huojiweiguoba/lbw.py
huojiweiguoba/lbw_datetime.py
huojiweiguoba/lbw_json.py
huojiweiguoba/lbw_math.py
huojiweiguoba/lbw_token.py
huojiweiguoba/main.py
huojiweiguoba/tools.py
huojiweiguoba/xx_read_listing.py
huojiweiguoba/ysgj_auto_parts_mysql_BC.py
huojiweiguoba/ysgj_feishu_sdk.py
huojiweiguoba/ysgj_mysql.py
huojiweiguoba/apis/__init__.py
huojiweiguoba/apis/oss.py
huojiweiguoba/eagle/__init__.py
huojiweiguoba/eagle/file.py
huojiweiguoba/eagle/folder.py
huojiweiguoba/eagle/library.py
huojiweiguoba/eagle/ys_car_master.py
huojiweiguoba-38.8.dist-info/LICENSE
huojiweiguoba-38.8.dist-info/METADATA
huojiweiguoba-38.8.dist-info/WHEEL
huojiweiguoba-38.8.dist-info/top_level.txt
huojiweiguoba-38.8.dist-info/RECORD
