Metadata-Version: 2.1
Name: huojiweiguoba
Version: 38.8
Summary: 人生有梦 各自精彩
Home-page: https://github.com/ycyxycm/huojiweiguoba
Author: lbw
Author-email: 819577544@qq.com
License-File: LICENSE
Requires-Dist: peewee
Requires-Dist: pymysql
Requires-Dist: pandas
Requires-Dist: python-dotenv
Requires-Dist: openpyxl
Requires-Dist: passlib
